oooscript/.oooscript_root
oooscript/__init__.py
oooscript/build/__init__.py
oooscript/build/build.py
oooscript/build/build2.py
oooscript/build/build_util.py
oooscript/build/builder_base.py
oooscript/build/copy_resource.py
oooscript/build/embed_py_script.py
oooscript/build/manifest_script.py
oooscript/build/tmp_dir.py
oooscript/cfg/__init__.py
oooscript/cfg/config.py
oooscript/cli/__init__.py
oooscript/cli/main.py
oooscript/lib/__init__.py
oooscript/lib/enums.py
oooscript/lib/ex.py
oooscript/models/__init__.py
oooscript/models/validators.py
oooscript/models/script_cfg/__init__.py
oooscript/models/script_cfg/args.py
oooscript/models/script_cfg/model_script_cfg.py
oooscript/res/__init__.py
oooscript/res/code/__init__.py
oooscript/res/code/prelude_pyz.py
oooscript/res/docs/__init__.py
oooscript/res/docs/blank.odf
oooscript/res/docs/blank.odg
oooscript/res/docs/blank.odp
oooscript/res/docs/blank.ods
oooscript/res/docs/blank.odt
oooscript/utils/__init__.py
oooscript/utils/enum_util.py
oooscript/utils/paths.py
oooscript-2.1.1.dist-info/METADATA
oooscript-2.1.1.dist-info/WHEEL
oooscript-2.1.1.dist-info/entry_points.txt
oooscript-2.1.1.dist-info/licenses/LICENSE
oooscript-2.1.1.dist-info/RECORD
