Metadata-Version: 2.3
Name: oooscript
Version: 2.1.1
Summary: Compiles several python scripts into a single script that can be easily used by LibreOffice as a macro.
Project-URL: Homepage, https://github.com/Amourspirit/python_libreoffice_oooscript
Project-URL: Documentation, https://oooscript.readthedocs.io/en/latest/
Project-URL: Repository, https://github.com/Amourspirit/python_libreoffice_oooscript
Project-URL: Issues, https://github.com/Amourspirit/python_libreoffice_oooscript/issues
Author-email: ":Barry-Thomas-Paul: Moss" <bigbytetech@gmail.com>
License: 
Keywords: libreoffice,macro,ooouno,pyuno,scriptmerge,uno
Classifier: Environment :: Other Environment
Classifier: Intended Audience :: Developers
Classifier: License :: OSI Approved :: Apache Software License
Classifier: Operating System :: OS Independent
Classifier: Programming Language :: Python
Classifier: Programming Language :: Python :: 3
Classifier: Programming Language :: Python :: 3.8
Classifier: Programming Language :: Python :: 3.9
Classifier: Programming Language :: Python :: 3.10
Classifier: Programming Language :: Python :: 3.11
Classifier: Programming Language :: Python :: 3.12
Classifier: Programming Language :: Python :: 3.13
Classifier: Topic :: Office/Business
Classifier: Topic :: Software Development :: Build Tools
Classifier: Topic :: Software Development :: Libraries :: Python Modules
Requires-Python: >=3.8
Requires-Dist: pydantic<2.0.0,>=1.10.2
Requires-Dist: python-dotenv>=1.0.1
Requires-Dist: scriptmerge>=3.1.0
